panza/__init__.py
panza/backends/__init__.py
panza/backends/_docker_builder.py
panza/backends/_docker_daemon.py
panza/backends/_utils.py
panza/backends/docker.py
panza/backends/ignite.py
panza/cache.py
panza/errors.py
panza/executor.py
panza/internals/blueprint.py
panza/internals/build.py
panza/internals/pipe_stream.py
panza/internals/result_serialization.py
panza/internals/workspace.py
panza/metadata.py
etna_panza-4.2.0.dist-info/METADATA
etna_panza-4.2.0.dist-info/WHEEL
etna_panza-4.2.0.dist-info/entry_points.txt
etna_panza-4.2.0.dist-info/RECORD
