Metadata-Version: 2.1
Name: etna-panza
Version: 4.2.0
Summary: Library to manage environments and jobs based on Quixote blueprints
License: MIT
Author: Clément "Doom" Doumergue
Author-email: clement.doumergue@etna.io
Requires-Python: >=3.8,<4.0
Classifier: License :: OSI Approved :: MIT License
Classifier: Programming Language :: Python :: 3
Classifier: Programming Language :: Python :: 3.8
Classifier: Programming Language :: Python :: 3.9
Classifier: Programming Language :: Python :: 3.10
Classifier: Programming Language :: Python :: 3.11
Requires-Dist: etna-quixote (>=2.0.0,<3.0.0)
